{
  "run_id": "quant_tutorial_20260601T104605Z",
  "timestamp": "2026-06-01T10:46:05.063740+00:00",
  "command": "python examples/quant_trading/scripts/run_column_05_pairs_spread_decomposition.py",
  "dataset": "market_ohlcv_pair_spreads",
  "strategies": [
    "classic_pair_ratio_zscore_120",
    "detime_spread_trend_drift_blocker",
    "detime_spread_residual_z",
    "detime_spread_cycle_timed",
    "classic_pair_spread_zscore_120",
    "classic_pair_corr_filtered_zscore"
  ],
  "status": "completed",
  "failure_reason": null,
  "result_file": "examples\\quant_trading\\reports\\column_05_strategy_comparison.csv",
  "python_version": "3.11.9",
  "platform": "Windows-10-10.0.26200-SP0"
}
